onepipepy/__init__.py
onepipepy/api.py
onepipepy/errors.py
onepipepy/models.py
onepipepy/utils.py
onepipepy/webhook.py
onepipepy-0.2.0.dist-info/LICENSE
onepipepy-0.2.0.dist-info/METADATA
onepipepy-0.2.0.dist-info/WHEEL
onepipepy-0.2.0.dist-info/top_level.txt
onepipepy-0.2.0.dist-info/RECORD
