Metadata-Version: 2.1
Name: onepipepy
Version: 0.2.0
Summary: A simple pythonic interface for PipeDrive API and Webhooks
Home-page: https://github.com/oneassure-tech/onepipepy
Author: OneAssure
Author-email: tech@oneassure.in
License: UNKNOWN
Project-URL: Bug Tracker, https://github.com/oneassure-tech/onepipepy/issues
Platform: UNKNOWN
Classifier: Programming Language :: Python :: 3
Classifier: License :: OSI Approved :: MIT License
Classifier: Operating System :: OS Independent
Requires-Python: >=3.6
License-File: LICENSE
